fastcosine/__init__.py
fastcosine/fastcosine.py
fastcosine-0.1.0.dist-info/DESCRIPTION.rst
fastcosine-0.1.0.dist-info/METADATA
fastcosine-0.1.0.dist-info/RECORD
fastcosine-0.1.0.dist-info/WHEEL
fastcosine-0.1.0.dist-info/metadata.json
fastcosine-0.1.0.dist-info/top_level.txt
